<annotation>
	<folder>n03036469</folder>
	<filename>n03036469_12573</filename>
	<source>
		<database>ImageNet database</database>
	</source>
	<size>
		<width>500</width>
		<height>375</height>
		<depth>3</depth>
	</size>
	<segmented>0</segmented>
	<object>
		<name>n03036469</name>
		<pose>Unspecified</pose>
		<truncated>0</truncated>
		<difficult>0</difficult>
		<bndbox>
			<xmin>254</xmin>
			<ymin>256</ymin>
			<xmax>482</xmax>
			<ymax>374</ymax>
		</bndbox>
	</object>
	<object>
		<name>n03036469</name>
		<pose>Unspecified</pose>
		<truncated>0</truncated>
		<difficult>0</difficult>
		<bndbox>
			<xmin>31</xmin>
			<ymin>172</ymin>
			<xmax>283</xmax>
			<ymax>374</ymax>
		</bndbox>
	</object>
</annotation>